[
	{ "s": "К", "p": [20, 19, 17, 6, 11, 10, 12] },
	{ "s": "КАВЫЧЕК", "p": [19, 7] },
	{ "s": "КАЖДОЕ", "p": [20, 7] },
	{ "s": "КАЖДОЙ", "p": [20] },
	{ "s": "КАЖДОМ", "p": [20, 19] },
	{ "s": "КАЖДОМУ", "p": [20] },
	{ "s": "КАЖДЫЙ", "p": [19, 10, 7, 6] },
	{ "s": "КАК", "p": [20, 19, 6] },
	{ "s": "КАКИЕ", "p": [20] },
	{ "s": "КАКОЕ", "p": [20] },
	{ "s": "КАКОЙ", "p": [20, 19] },
	{ "s": "КАРТИНКЕ", "p": [6] },
	{ "s": "КАРТИНКИ", "p": [6] },
	{ "s": "КАРТИНКОЙ", "p": [19, 6] },
	{ "s": "КАТАЛОГ", "p": [12, 20] },
	{ "s": "КАТАЛОГА", "p": [20, 11, 10] },
	{ "s": "КАТАЛОГЕ", "p": [12] },
	{ "s": "КАТАЛОГИ", "p": [20] },
	{ "s": "КАТАЛОГУ", "p": [11, 10] },
	{ "s": "КАЧАТЬ", "p": [20] },
	{ "s": "КЛАВИАТУРЕ", "p": [12] },
	{ "s": "КЛИЕНТ", "p": [20, 12, 6] },
	{ "s": "КЛИЕНТА", "p": [12, 20, 10, 6, 18, 17, 11] },
	{ "s": "КЛИЕНТАМИ", "p": [14] },
	{ "s": "КЛИЕНТЕ", "p": [20] },
	{ "s": "КЛИЕНТОМ", "p": [20, 10] },
	{ "s": "КЛИЕНТСКАЯ", "p": [7] },
	{ "s": "КЛЮЧЕВОЕ", "p": [15, 12] },
	{ "s": "КЛЮЧЕВЫЕ", "p": [12] },
	{ "s": "КНОПКА", "p": [11, 10] },
	{ "s": "КНОПКИ", "p": [19] },
	{ "s": "КНОПКОЙ", "p": [19] },
	{ "s": "КНОПКУ", "p": [20, 19, 12, 7] },
	{ "s": "КНОПОК", "p": [6] },
	{ "s": "КОГДА", "p": [20, 19] },
	{ "s": "КОЛИЧЕСТВА", "p": [14] },
	{ "s": "КОЛИЧЕСТВО", "p": [20, 17, 16, 14, 12, 10] },
	{ "s": "КОЛИЧЕСТВОМ", "p": [14] },
	{ "s": "КОЛОНКА", "p": [20] },
	{ "s": "КОЛОНКИ", "p": [20] },
	{ "s": "КОМАНДА", "p": [11, 10] },
	{ "s": "КОМПОНЕНТОВ", "p": [7] },
	{ "s": "КОНТРОЛЬ", "p": [20] },
	{ "s": "КОНТРОЛЬНЫЕ", "p": [10, 11] },
	{ "s": "КОНТРОЛЬНЫХ", "p": [11, 10] },
	{ "s": "КОНФИГУРАЦИОННЫЙ", "p": [13] },
	{ "s": "КООРДИНАТОЙ", "p": [19, 7] },
	{ "s": "КОРНЕ", "p": [20] },
	{ "s": "КОРНЕВОЙ", "p": [20] },
	{ "s": "КОРРЕКТНОЙ", "p": [20] },
	{ "s": "КОСВЕННОЕ", "p": [12] },
	{ "s": "КОТОРАЯ", "p": [19, 17] },
	{ "s": "КОТОРОЕ", "p": [20, 16] },
	{ "s": "КОТОРОЙ", "p": [19, 6] },
	{ "s": "КОТОРОМ", "p": [12, 20, 19] },
	{ "s": "КОТОРОМУ", "p": [6] },
	{ "s": "КОТОРУЮ", "p": [19] },
	{ "s": "КОТОРЫЕ", "p": [20, 17, 12, 13, 7, 6] },
	{ "s": "КОТОРЫЙ", "p": [12, 20, 19, 6, 17, 7] },
	{ "s": "КОТОРЫХ", "p": [12] },
	{ "s": "КРАЯ", "p": [7] },
	{ "s": "КРИТИЧЕСКИЕ", "p": [20, 18] },
	{ "s": "КРИТИЧЕСКИХ", "p": [20, 12] }
]